README.md
setup.py
dictsorted/__init__.py
dictsorted/dictsorted.py
dictsorted.egg-info/PKG-INFO
dictsorted.egg-info/SOURCES.txt
dictsorted.egg-info/dependency_links.txt
dictsorted.egg-info/top_level.txt