Metadata-Version: 1.0
Name: dictsorted
Version: 0.0.6
Summary: return [sorted(dict.key||value)]
Home-page: https://github.com/lucyking/dictsorted
Author: lucyking
Author-email: joehisaishi1943@gmail.com
License: UNKNOWN
Platform: UNKNOWN
